xml2gui/__init__.py
xml2gui/compiler.py
xml2gui/generator.py
xml2gui/parser.py
xml2gui-1.0.0.dist-info/LICENSE-SCL
xml2gui-1.0.0.dist-info/METADATA
xml2gui-1.0.0.dist-info/WHEEL
xml2gui-1.0.0.dist-info/entry_points.txt
xml2gui-1.0.0.dist-info/top_level.txt
xml2gui-1.0.0.dist-info/RECORD
