Metadata-Version: 2.1
Name: xml2gui
Version: 1.0.0
Summary: A powerful framework for creating GUI applications using XML files
Home-page: https://gitee.com/ghhuang1057/xml2-gui
Author: huang1057
Author-email: your.email@example.com
License: UNKNOWN
Project-URL: Documentation, https://gitee.com/ghhuang1057/xml2-gui/blob/master/USER_GUIDE.md
Project-URL: Source, https://gitee.com/ghhuang1057/xml2-gui
Project-URL: Bug Reports, https://gitee.com/ghhuang1057/xml2-gui/issues
Keywords: xml gui pyqt pyqt5 qt python ui designer
Platform: UNKNOWN
Classifier: Development Status :: 4 - Beta
Classifier: Intended Audience :: Developers
Classifier: License :: OSI Approved :: GNU General Public License v3 (GPLv3)
Classifier: Programming Language :: Python :: 3
Classifier: Programming Language :: Python :: 3.6
Classifier: Programming Language :: Python :: 3.7
Classifier: Programming Language :: Python :: 3.8
Classifier: Programming Language :: Python :: 3.9
Classifier: Programming Language :: Python :: 3.10
Classifier: Programming Language :: Python :: 3.11
Classifier: Operating System :: OS Independent
Classifier: Topic :: Software Development :: User Interfaces
Classifier: Topic :: Software Development :: Code Generators
Requires-Python: >=3.6
License-File: LICENSE-SCL
Requires-Dist: PyQt5>=5.15.0
Requires-Dist: PyQt-Fluent-Widgets>=1.0.0
Requires-Dist: nuitka>=1.5.0
